jot/__init__.py
jot/base.py
jot/decorators.py
jot/facade.py
jot/fanout.py
jot/flush.py
jot/log.py
jot/pg.py
jot/print.py
jot/rollbar.py
jot/util.py
jot/zipkin.py
dl_jot-0.8.dist-info/WHEEL
dl_jot-0.8.dist-info/METADATA
dl_jot-0.8.dist-info/licenses/LICENSE
dl_jot-0.8.dist-info/licenses/AUTHORS
dl_jot-0.8.dist-info/RECORD
